ave/VERSION
ave/__init__.py
ave/__main__.py
ave/ave.py
ave/config.py
ave/exceptions.py
ave/game.py
ave/gamelist.json
ave/_games/make.ave
ave/_games/moscow.ave
ave/_games/murder.ave
ave/_games/random.ave
ave/_games/shop.ave
ave/_games/tea.ave
ave/_games/test.ave
ave/components/__init__.py
ave/components/item_giver.py
ave/components/items.py
ave/components/numbers.py
ave/components/requirements.py
ave/components/with_requirements.py
ave/display/__init__.py
ave/display/base.py
ave/display/curses_screen.py
ave/parsing/__init__.py
ave/parsing/file_parsing.py
ave/parsing/game_loader.py
ave/parsing/string_functions.py
ave/screens/credits
ave/screens/title
ave/screens/user
ave/test/__init__.py
ave/test/error_handlers.py
ave/test/game_validation.py
avegame-1.9.8.data/data/ave/VERSION
avegame-1.9.8.data/data/ave/gamelist.json
avegame-1.9.8.data/data/ave/_games/make.ave
avegame-1.9.8.data/data/ave/_games/moscow.ave
avegame-1.9.8.data/data/ave/_games/murder.ave
avegame-1.9.8.data/data/ave/_games/random.ave
avegame-1.9.8.data/data/ave/_games/shop.ave
avegame-1.9.8.data/data/ave/_games/tea.ave
avegame-1.9.8.data/data/ave/_games/test.ave
avegame-1.9.8.data/data/ave/screens/credits
avegame-1.9.8.data/data/ave/screens/title
avegame-1.9.8.data/data/ave/screens/user
avegame-1.9.8.dist-info/LICENSE.txt
avegame-1.9.8.dist-info/METADATA
avegame-1.9.8.dist-info/WHEEL
avegame-1.9.8.dist-info/entry_points.txt
avegame-1.9.8.dist-info/top_level.txt
avegame-1.9.8.dist-info/RECORD
